ems_cli/__init__.py
ems_cli/__main__.py
ems_cli/add_group_name_alias.py
ems_cli/add_stream_alias.py
ems_cli/create_dash_stream.py
ems_cli/create_hds_stream.py
ems_cli/create_hls_stream.py
ems_cli/create_ingest_point.py
ems_cli/create_mss_stream.py
ems_cli/flush_group_name_aliases.py
ems_cli/flush_stream_aliases.py
ems_cli/get_config_info.py
ems_cli/get_group_name_by_alias.py
ems_cli/get_stream_info.py
ems_cli/get_streams_count.py
ems_cli/is_stream_running.py
ems_cli/list_config.py
ems_cli/list_group_name_aliases.py
ems_cli/list_http_streaming_sessions.py
ems_cli/list_ingest_points.py
ems_cli/list_stream_aliases.py
ems_cli/list_streams.py
ems_cli/list_streams_ids.py
ems_cli/pull_stream.py
ems_cli/push_stream.py
ems_cli/record.py
ems_cli/remove_config.py
ems_cli/remove_group_name_alias.py
ems_cli/remove_ingest_point.py
ems_cli/remove_stream_alias.py
ems_cli/shutdown_stream.py
ems_cli/transcode.py
ems_cli/utils.py
ems_cli-0.1.0b1.dist-info/DESCRIPTION.rst
ems_cli-0.1.0b1.dist-info/METADATA
ems_cli-0.1.0b1.dist-info/RECORD
ems_cli-0.1.0b1.dist-info/WHEEL
ems_cli-0.1.0b1.dist-info/entry_points.txt
ems_cli-0.1.0b1.dist-info/metadata.json
ems_cli-0.1.0b1.dist-info/top_level.txt
