Metadata-Version: 2.0
Name: ems-cli
Version: 0.1.0b1
Summary: CLI for EVO Media Server
Home-page: https://github.com/tomi77/ems-cli
Author: Tomasz Jakub Rup
Author-email: tomasz.rup@gmail.com
License: MIT
Platform: UNKNOWN
Classifier: Development Status :: 4 - Beta
Classifier: Intended Audience :: Developers
Classifier: License :: OSI Approved :: MIT License
Classifier: Operating System :: OS Independent
Classifier: Programming Language :: Python
Classifier: Programming Language :: Python :: 2.7
Classifier: Programming Language :: Python :: 3
Classifier: Programming Language :: Python :: 3.2
Classifier: Programming Language :: Python :: 3.3
Classifier: Programming Language :: Python :: 3.4
Classifier: Programming Language :: Python :: 3.5
Classifier: Topic :: Multimedia :: Video
Requires-Dist: pyems (>=0.1.2)
